[{"url": "https://www.python.org/ftp/python/3.11.0/Python-3.11.0b5.tgz", "sha256": "3f7d1a4ab0e64425f4ffd92d49de192ad2ee1c62bc52e3877e9f7b254c702e60", "raw": {"Version": "https://www.python.org/ftp/python/3.11.0/Python-3.11.0b5.tgz", "Operating System": "Source release", "Description": null, "MD5 Sum": "944a2913ed45e8111f4169230f24556c", "File Size": "25.1\u00a0MB", "GPG": "https://www.python.org/ftp/python/3.11.0/Python-3.11.0b5.tgz.asc"}}, {"url": "https://www.python.org/ftp/python/3.11.0/Python-3.11.0b5.tar.xz", "sha256": "3810bd22f7dc34a99c2a2eb4b85264a4df4f05ef59c4e0ccc2ea82ee9c491698", "raw": {"Version": "https://www.python.org/ftp/python/3.11.0/Python-3.11.0b5.tar.xz", "Operating System": "Source release", "Description": null, "MD5 Sum": "ef72213a60146324699c48344b4ea31c", "File Size": "18.9\u00a0MB", "GPG": "https://www.python.org/ftp/python/3.11.0/Python-3.11.0b5.tar.xz.asc"}}, {"url": "https://www.python.org/ftp/python/3.11.0/python-3.11.0b5-macos11.pkg", "sha256": "cd8e6d98e79a4adcd376c486405a535b004cf9a58a71487a11bc424acd815012", "raw": {"Version": "https://www.python.org/ftp/python/3.11.0/python-3.11.0b5-macos11.pkg", "Operating System": "macOS", "Description": "for macOS 10.9 and later", "MD5 Sum": "df1da04df4fc0593844f6ff161f38e54", "File Size": "40.5\u00a0MB", "GPG": "https://www.python.org/ftp/python/3.11.0/python-3.11.0b5-macos11.pkg.asc"}}, {"url": "https://www.python.org/ftp/python/3.11.0/python-3.11.0b5-amd64.exe", "sha256": "0cf9d582da862f2fe207fd54b81dfca110e8f04f4b05ab8c3228ce1ea060c7af", "raw": {"Version": "https://www.python.org/ftp/python/3.11.0/python-3.11.0b5-amd64.exe", "Operating System": "Windows", "Description": "Recommended", "MD5 Sum": "eec2c4ce1fc1f8314f6a244b88e49516", "File Size": "24.0\u00a0MB", "GPG": "https://www.python.org/ftp/python/3.11.0/python-3.11.0b5-amd64.exe.asc"}}, {"url": "https://www.python.org/ftp/python/3.11.0/python-3.11.0b5.exe", "sha256": "382eb4c6dc1606bd3cf6f4bdeec8e1e7dab444c5aa23b86142d608a480d7c195", "raw": {"Version": "https://www.python.org/ftp/python/3.11.0/python-3.11.0b5.exe", "Operating System": "Windows", "Description": null, "MD5 Sum": "264f8a790c8acf955a8a4d16043da044", "File Size": "22.9\u00a0MB", "GPG": "https://www.python.org/ftp/python/3.11.0/python-3.11.0b5.exe.asc"}}, {"url": "https://www.python.org/ftp/python/3.11.0/python-3.11.0b5-arm64.exe", "sha256": "a71efd9d3835d493d8207a30916ce3417af17295c02a9b0783dc740754f6e40b", "raw": {"Version": "https://www.python.org/ftp/python/3.11.0/python-3.11.0b5-arm64.exe", "Operating System": "Windows", "Description": "Experimental", "MD5 Sum": "0f054c36d6898ead697bad2f8ad0a85e", "File Size": "23.1\u00a0MB", "GPG": "https://www.python.org/ftp/python/3.11.0/python-3.11.0b5-arm64.exe.asc"}}, {"url": "https://www.python.org/ftp/python/3.11.0/python-3.11.0b5-embed-amd64.zip", "sha256": "5584ddbd21f45ce74ce0512eeb1d817d15374b1b7a461d79f973f6dd48ab5d9e", "raw": {"Version": "https://www.python.org/ftp/python/3.11.0/python-3.11.0b5-embed-amd64.zip", "Operating System": "Windows", "Description": null, "MD5 Sum": "1a1e37c146e4d2aafb846550e1c8d52f", "File Size": "10.0\u00a0MB", "GPG": "https://www.python.org/ftp/python/3.11.0/python-3.11.0b5-embed-amd64.zip.asc"}}, {"url": "https://www.python.org/ftp/python/3.11.0/python-3.11.0b5-embed-win32.zip", "sha256": "18927604bcbe3c226be7864cde0c1f25ad35c6333d9d3125dfff8ca4fc872255", "raw": {"Version": "https://www.python.org/ftp/python/3.11.0/python-3.11.0b5-embed-win32.zip", "Operating System": "Windows", "Description": null, "MD5 Sum": "94b7bd9732c8c0cfa7076a5c91fc0ee8", "File Size": "9.1\u00a0MB", "GPG": "https://www.python.org/ftp/python/3.11.0/python-3.11.0b5-embed-win32.zip.asc"}}, {"url": "https://www.python.org/ftp/python/3.11.0/python-3.11.0b5-embed-arm64.zip", "sha256": "819924f10eb08ea6322b6040a2fb953137866bb1034cd4e8fe6e93c7c0b37e31", "raw": {"Version": "https://www.python.org/ftp/python/3.11.0/python-3.11.0b5-embed-arm64.zip", "Operating System": "Windows", "Description": null, "MD5 Sum": "3572178d23f692f2870f46816b4a31cf", "File Size": "9.3\u00a0MB", "GPG": "https://www.python.org/ftp/python/3.11.0/python-3.11.0b5-embed-arm64.zip.asc"}}]