[
    {
        "raw": {
            "Description": null,
            "File Size": "25.0\u00a0MB",
            "GPG": "https://www.python.org/ftp/python/3.12.0/Python-3.12.0a2.tgz.sig",
            "MD5 Sum": "4939e2d3ca0eae41ca57e61eecb263da",
            "Operating System": "Source release",
            "Sigstore": "https://www.python.org/ftp/python/3.12.0/Python-3.12.0a2.tgz.crt",
            "Version": "https://www.python.org/ftp/python/3.12.0/Python-3.12.0a2.tgz"
        },
        "release_url": "https://www.python.org/downloads/release/python-3120a2/",
        "sha256": "81fa3468cada25f5ac8868230a847999495464f8ab67df1df3e8e8e280df0b2b",
        "url": "https://www.python.org/ftp/python/3.12.0/Python-3.12.0a2.tgz"
    },
    {
        "raw": {
            "Description": null,
            "File Size": "18.7\u00a0MB",
            "GPG": "https://www.python.org/ftp/python/3.12.0/Python-3.12.0a2.tar.xz.sig",
            "MD5 Sum": "100ec555643cef2c0fe3a738bb248403",
            "Operating System": "Source release",
            "Sigstore": "https://www.python.org/ftp/python/3.12.0/Python-3.12.0a2.tar.xz.crt",
            "Version": "https://www.python.org/ftp/python/3.12.0/Python-3.12.0a2.tar.xz"
        },
        "release_url": "https://www.python.org/downloads/release/python-3120a2/",
        "sha256": "1eafc1384e532cac6432632a77350ef504a114c4235c1f6f2a85f817f5b1926a",
        "url": "https://www.python.org/ftp/python/3.12.0/Python-3.12.0a2.tar.xz"
    },
    {
        "raw": {
            "Description": "for macOS 10.9 and later",
            "File Size": "40.3\u00a0MB",
            "GPG": "https://www.python.org/ftp/python/3.12.0/python-3.12.0a2-macos11.pkg.sig",
            "MD5 Sum": "a45b49658118e4abab68202ef4f16a0b",
            "Operating System": "macOS",
            "Sigstore": "https://www.python.org/ftp/python/3.12.0/python-3.12.0a2-macos11.pkg.crt",
            "Version": "https://www.python.org/ftp/python/3.12.0/python-3.12.0a2-macos11.pkg"
        },
        "release_url": "https://www.python.org/downloads/release/python-3120a2/",
        "sha256": "3b0fb8122782c7803f3869a43888955953da187676c389d24c441f061a8914b4",
        "url": "https://www.python.org/ftp/python/3.12.0/python-3.12.0a2-macos11.pkg"
    },
    {
        "raw": {
            "Description": "Recommended",
            "File Size": "23.8\u00a0MB",
            "GPG": "https://www.python.org/ftp/python/3.12.0/python-3.12.0a2-amd64.exe.sig",
            "MD5 Sum": "96e2b9aff5b46adb95b7285bcbcb165e",
            "Operating System": "Windows",
            "Sigstore": "https://www.python.org/ftp/python/3.12.0/python-3.12.0a2-amd64.exe.crt",
            "Version": "https://www.python.org/ftp/python/3.12.0/python-3.12.0a2-amd64.exe"
        },
        "release_url": "https://www.python.org/downloads/release/python-3120a2/",
        "sha256": "ea5d760b4f7023f5ae60a369674a7e3f9fd2a7561d1d1f901e03f0f80c7c0f9c",
        "url": "https://www.python.org/ftp/python/3.12.0/python-3.12.0a2-amd64.exe"
    },
    {
        "raw": {
            "Description": null,
            "File Size": "22.7\u00a0MB",
            "GPG": "https://www.python.org/ftp/python/3.12.0/python-3.12.0a2.exe.sig",
            "MD5 Sum": "f08f1bdc3c6ea4d79c3848d0d37f3d29",
            "Operating System": "Windows",
            "Sigstore": "https://www.python.org/ftp/python/3.12.0/python-3.12.0a2.exe.crt",
            "Version": "https://www.python.org/ftp/python/3.12.0/python-3.12.0a2.exe"
        },
        "release_url": "https://www.python.org/downloads/release/python-3120a2/",
        "sha256": "4eaf6cdf229c1cd129ccadc701c2f09450288872aed4394d57e545f0610d86c4",
        "url": "https://www.python.org/ftp/python/3.12.0/python-3.12.0a2.exe"
    },
    {
        "raw": {
            "Description": "Experimental",
            "File Size": "23.0\u00a0MB",
            "GPG": "https://www.python.org/ftp/python/3.12.0/python-3.12.0a2-arm64.exe.sig",
            "MD5 Sum": "33b1a5a147effccd00813fd28aabacea",
            "Operating System": "Windows",
            "Sigstore": "https://www.python.org/ftp/python/3.12.0/python-3.12.0a2-arm64.exe.crt",
            "Version": "https://www.python.org/ftp/python/3.12.0/python-3.12.0a2-arm64.exe"
        },
        "release_url": "https://www.python.org/downloads/release/python-3120a2/",
        "sha256": "55b6a273ea388cc821615e72e130c79a62d00016e1b3c5a572f6edc0a8ce6206",
        "url": "https://www.python.org/ftp/python/3.12.0/python-3.12.0a2-arm64.exe"
    },
    {
        "raw": {
            "Description": null,
            "File Size": "9.8\u00a0MB",
            "GPG": "https://www.python.org/ftp/python/3.12.0/python-3.12.0a2-embed-amd64.zip.sig",
            "MD5 Sum": "8b77c757682bba0a68540c08e66a0497",
            "Operating System": "Windows",
            "Sigstore": "https://www.python.org/ftp/python/3.12.0/python-3.12.0a2-embed-amd64.zip.crt",
            "Version": "https://www.python.org/ftp/python/3.12.0/python-3.12.0a2-embed-amd64.zip"
        },
        "release_url": "https://www.python.org/downloads/release/python-3120a2/",
        "sha256": "2794dda7cd472c452e6428f827a78077634a169e14e5657cb3ad5929545a87cf",
        "url": "https://www.python.org/ftp/python/3.12.0/python-3.12.0a2-embed-amd64.zip"
    },
    {
        "raw": {
            "Description": null,
            "File Size": "8.8\u00a0MB",
            "GPG": "https://www.python.org/ftp/python/3.12.0/python-3.12.0a2-embed-win32.zip.sig",
            "MD5 Sum": "fdb55ed9ec76e156794b8fc93ab7179e",
            "Operating System": "Windows",
            "Sigstore": "https://www.python.org/ftp/python/3.12.0/python-3.12.0a2-embed-win32.zip.crt",
            "Version": "https://www.python.org/ftp/python/3.12.0/python-3.12.0a2-embed-win32.zip"
        },
        "release_url": "https://www.python.org/downloads/release/python-3120a2/",
        "sha256": "e57b02f5de3d7ba40459cab30b00b1a54e15564b776fd083e2597f652b33031c",
        "url": "https://www.python.org/ftp/python/3.12.0/python-3.12.0a2-embed-win32.zip"
    },
    {
        "raw": {
            "Description": null,
            "File Size": "9.0\u00a0MB",
            "GPG": "https://www.python.org/ftp/python/3.12.0/python-3.12.0a2-embed-arm64.zip.sig",
            "MD5 Sum": "defdea44ee784cacf21a3c4227d7ebd7",
            "Operating System": "Windows",
            "Sigstore": "https://www.python.org/ftp/python/3.12.0/python-3.12.0a2-embed-arm64.zip.crt",
            "Version": "https://www.python.org/ftp/python/3.12.0/python-3.12.0a2-embed-arm64.zip"
        },
        "release_url": "https://www.python.org/downloads/release/python-3120a2/",
        "sha256": "639e08d51115d50c67e0d9544037fc06f0ad3dce3d4fd580d79f7f87dc2be6a0",
        "url": "https://www.python.org/ftp/python/3.12.0/python-3.12.0a2-embed-arm64.zip"
    }
]