[
    {
        "raw": {
            "description": null,
            "filesize": 26903080,
            "md5": "4d14e8b8bb6d694af37625beabee6069",
            "sha256": null,
            "sigstore": null,
            "slug": "python-335rc2",
            "url": "http://www.python.org/ftp/python/3.3.5/python-3.3.5rc2-pdb.zip"
        },
        "sha256": "70ffa117447373562e6e6c4a5566b2a10e6fd8a9e79cad279f9d785eed143e56"
    },
    {
        "raw": {
            "description": null,
            "filesize": 6705379,
            "md5": "992e94fca4ae09d31246a3d6c5f87748",
            "sha256": null,
            "sigstore": null,
            "slug": "python-335rc2",
            "url": "http://www.python.org/ftp/python/3.3.5/python335rc2.chm"
        },
        "sha256": "c94c2dee5da8ebbca7e17844ead4d00e52ebc9d345e3eaec7abbf03a22e4620f"
    },
    {
        "raw": {
            "description": null,
            "filesize": 20672512,
            "md5": "ff43520e8f1fdf86dd1e2fa05299e77b",
            "sha256": null,
            "sigstore": null,
            "slug": "python-335rc2",
            "url": "http://www.python.org/ftp/python/3.3.5/python-3.3.5rc2.msi"
        },
        "sha256": "8e103a369f6812666a4bacdaec9a5be3b37b128aee814e7f2db66cc56cd8b301"
    },
    {
        "raw": {
            "description": "for AMD64/EM64T/x64",
            "filesize": 21217280,
            "md5": "15534a04a832fde3137d756f8d2a2833",
            "sha256": null,
            "sigstore": null,
            "slug": "python-335rc2",
            "url": "http://www.python.org/ftp/python/3.3.5/python-3.3.5rc2.amd64.msi"
        },
        "sha256": "6ec587aa7d1eebbcae9add2fd08313cd482e048b964b13e413c5ec07a1a5eaf5"
    },
    {
        "raw": {
            "description": "for Mac OS X 10.5 and later",
            "filesize": 19965085,
            "md5": "9c18fb0aa68cf3c17eaf63079295b6e3",
            "sha256": null,
            "sigstore": null,
            "slug": "python-335rc2",
            "url": "http://www.python.org/ftp/python/3.3.5/python-3.3.5rc2-macosx10.5.dmg"
        },
        "sha256": "9f11def7e0ed3db623d8f3682fb06251b927e4754773c5274c7d82086ab830d3"
    },
    {
        "raw": {
            "description": "for Mac OS X 10.6 and later",
            "filesize": 20021227,
            "md5": "11d0a88e15c4882dc30271dcf9341bf9",
            "sha256": null,
            "sigstore": null,
            "slug": "python-335rc2",
            "url": "http://www.python.org/ftp/python/3.3.5/python-3.3.5rc2-macosx10.6.dmg"
        },
        "sha256": "e223958d80c19da8fbbac4305ea99c6a9be9ca79cc420e12ea52292d3ad54471"
    },
    {
        "raw": {
            "description": null,
            "filesize": 16881986,
            "md5": "45a6adb9cca2a90eab9270d4eadb2e00",
            "sha256": null,
            "sigstore": null,
            "slug": "python-335rc2",
            "url": "http://www.python.org/ftp/python/3.3.5/Python-3.3.5rc2.tgz"
        },
        "sha256": "ccc196cfe4e8e397eca6959c086acb45941d0b7efc49d412c16049ca2b720146"
    },
    {
        "raw": {
            "description": null,
            "filesize": 12105636,
            "md5": "f8564947f4e4604e500cd3b802ff821d",
            "sha256": null,
            "sigstore": null,
            "slug": "python-335rc2",
            "url": "http://www.python.org/ftp/python/3.3.5/Python-3.3.5rc2.tar.xz"
        },
        "sha256": "585a24d897d99e5b68d067d7cb481f1dc7e79cc5676acb36aadae68f1bedc276"
    }
]