[
    {
        "raw": {
            "Description": null,
            "File Size": "18.7\u00a0MB",
            "GPG": "https://www.python.org/ftp/python/3.4.3/Python-3.4.3rc1.tgz.asc",
            "MD5 Sum": "fab0f871a76682882e080ac35439c09f",
            "Operating System": "Source release",
            "Version": "https://www.python.org/ftp/python/3.4.3/Python-3.4.3rc1.tgz"
        },
        "release_url": "https://www.python.org/downloads/release/python-343rc1/",
        "sha256": "e55c190f5c3d1a3c13e3cf6160a93540c6a562b515c30baba3b7b2a19b579672",
        "url": "https://www.python.org/ftp/python/3.4.3/Python-3.4.3rc1.tgz"
    },
    {
        "raw": {
            "Description": null,
            "File Size": "13.8\u00a0MB",
            "GPG": "https://www.python.org/ftp/python/3.4.3/Python-3.4.3rc1.tar.xz.asc",
            "MD5 Sum": "5bac881b3dd7cf4d0b6d6b733eb2affa",
            "Operating System": "Source release",
            "Version": "https://www.python.org/ftp/python/3.4.3/Python-3.4.3rc1.tar.xz"
        },
        "release_url": "https://www.python.org/downloads/release/python-343rc1/",
        "sha256": "dc4174d75ac1216b1a9c79797372e03791fb33b88f9ead6a7d692277735bf8d1",
        "url": "https://www.python.org/ftp/python/3.4.3/Python-3.4.3rc1.tar.xz"
    },
    {
        "raw": {
            "Description": "for Mac OS X 10.5 and later",
            "File Size": "23.6\u00a0MB",
            "GPG": "https://www.python.org/ftp/python/3.4.3/python-3.4.3rc1-macosx10.5.pkg.asc",
            "MD5 Sum": "359e9caacf9350cf9eb22ae66c374acf",
            "Operating System": "macOS",
            "Version": "https://www.python.org/ftp/python/3.4.3/python-3.4.3rc1-macosx10.5.pkg"
        },
        "release_url": "https://www.python.org/downloads/release/python-343rc1/",
        "sha256": "0afd4ab54a688c8220da92cb265612e6f96639de3919cdea8d4163f23af1c332",
        "url": "https://www.python.org/ftp/python/3.4.3/python-3.4.3rc1-macosx10.5.pkg"
    },
    {
        "raw": {
            "Description": "for Mac OS X 10.6 and later",
            "File Size": "22.1\u00a0MB",
            "GPG": "https://www.python.org/ftp/python/3.4.3/python-3.4.3rc1-macosx10.6.pkg.asc",
            "MD5 Sum": "f117f7291e17e1ee6c8685ff80a917ca",
            "Operating System": "macOS",
            "Version": "https://www.python.org/ftp/python/3.4.3/python-3.4.3rc1-macosx10.6.pkg"
        },
        "release_url": "https://www.python.org/downloads/release/python-343rc1/",
        "sha256": "0c55fad26807151de70cea28d279d30fd57a6433dee3e9ea6f26f7052dadf986",
        "url": "https://www.python.org/ftp/python/3.4.3/python-3.4.3rc1-macosx10.6.pkg"
    },
    {
        "raw": {
            "Description": null,
            "File Size": "7.1\u00a0MB",
            "GPG": "https://www.python.org/ftp/python/3.4.3/python343rc1.chm.asc",
            "MD5 Sum": "4b2483de7e96541150330be122f1656e",
            "Operating System": "Windows",
            "Version": "https://www.python.org/ftp/python/3.4.3/python343rc1.chm"
        },
        "release_url": "https://www.python.org/downloads/release/python-343rc1/",
        "sha256": "810b49dd5d830afc952186580d94092981f1d73a3c8b2ccb2ebc04f53504ba0d",
        "url": "https://www.python.org/ftp/python/3.4.3/python343rc1.chm"
    },
    {
        "raw": {
            "Description": null,
            "File Size": "35.2\u00a0MB",
            "GPG": "https://www.python.org/ftp/python/3.4.3/python-3.4.3rc1-pdb.zip.asc",
            "MD5 Sum": "c659c3c88b7d8637bfcf15ad9e09c96b",
            "Operating System": "Windows",
            "Version": "https://www.python.org/ftp/python/3.4.3/python-3.4.3rc1-pdb.zip"
        },
        "release_url": "https://www.python.org/downloads/release/python-343rc1/",
        "sha256": "5527e02637f0b4c47fb035ecc449a017a4e97ca7a7fe747a176abaab6ad18305",
        "url": "https://www.python.org/ftp/python/3.4.3/python-3.4.3rc1-pdb.zip"
    },
    {
        "raw": {
            "Description": null,
            "File Size": "23.1\u00a0MB",
            "GPG": "https://www.python.org/ftp/python/3.4.3/python-3.4.3rc1.amd64-pdb.zip.asc",
            "MD5 Sum": "5ff0c91d611796e06334c6ca375f54d8",
            "Operating System": "Windows",
            "Version": "https://www.python.org/ftp/python/3.4.3/python-3.4.3rc1.amd64-pdb.zip"
        },
        "release_url": "https://www.python.org/downloads/release/python-343rc1/",
        "sha256": "5e3d4189625c48f167100c294c8dbdb4663a00b27c423ba14115f6a95d4e884a",
        "url": "https://www.python.org/ftp/python/3.4.3/python-3.4.3rc1.amd64-pdb.zip"
    },
    {
        "raw": {
            "Description": null,
            "File Size": "23.6\u00a0MB",
            "GPG": "https://www.python.org/ftp/python/3.4.3/python-3.4.3rc1.msi.asc",
            "MD5 Sum": "008e6377367e618a4f178287cf013857",
            "Operating System": "Windows",
            "Version": "https://www.python.org/ftp/python/3.4.3/python-3.4.3rc1.msi"
        },
        "release_url": "https://www.python.org/downloads/release/python-343rc1/",
        "sha256": "bb21a27b5abffa63214f388731bfe83fa4c32973977292828cf5bf8c4f6af472",
        "url": "https://www.python.org/ftp/python/3.4.3/python-3.4.3rc1.msi"
    },
    {
        "raw": {
            "Description": "for AMD64/EM64T/x64",
            "File Size": "24.4\u00a0MB",
            "GPG": "https://www.python.org/ftp/python/3.4.3/python-3.4.3rc1.amd64.msi.asc",
            "MD5 Sum": "21146fe84fcc0b0d891f8870687f0081",
            "Operating System": "Windows",
            "Version": "https://www.python.org/ftp/python/3.4.3/python-3.4.3rc1.amd64.msi"
        },
        "release_url": "https://www.python.org/downloads/release/python-343rc1/",
        "sha256": "cace2df1a39d05c65c6f056e16c2ff6149b09e8fc1ba8d8f2f99b5e5d6172b3a",
        "url": "https://www.python.org/ftp/python/3.4.3/python-3.4.3rc1.amd64.msi"
    }
]