[
    {
        "url": "https://www.python.org/ftp/python/3.4.1/Python-3.4.1rc1.tgz",
        "sha256": "8b1557d635ee6eee04105f580877822a0b094945337ea780ed0f575ea4d15bb5",
        "release_url": "https://www.python.org/downloads/release/python-341rc1/",
        "raw": {
            "Version": "https://www.python.org/ftp/python/3.4.1/Python-3.4.1rc1.tgz",
            "Operating System": "Source release",
            "Description": null,
            "MD5 Sum": "618f398f53260dd50303795bbe432906",
            "File Size": "18.4\u00a0MB",
            "GPG": "https://www.python.org/ftp/python/3.4.1/Python-3.4.1rc1.tgz.asc"
        }
    },
    {
        "url": "https://www.python.org/ftp/python/3.4.1/Python-3.4.1rc1.tar.xz",
        "sha256": "d56bb10aafd6d4fec945aa4140c3aa1680f8a5142d128b53436047b2b317afc6",
        "release_url": "https://www.python.org/downloads/release/python-341rc1/",
        "raw": {
            "Version": "https://www.python.org/ftp/python/3.4.1/Python-3.4.1rc1.tar.xz",
            "Operating System": "Source release",
            "Description": null,
            "MD5 Sum": "fba41e2d0b26b9042791eff642428b14",
            "File Size": "13.5\u00a0MB",
            "GPG": "https://www.python.org/ftp/python/3.4.1/Python-3.4.1rc1.tar.xz.asc"
        }
    },
    {
        "url": "https://www.python.org/ftp/python/3.4.1/python-3.4.1rc1-macosx10.5.dmg",
        "sha256": "17ca1fab1f70f339b266bfa8aadfdccd030b4c21f6fa34384422e42ebaa1c630",
        "release_url": "https://www.python.org/downloads/release/python-341rc1/",
        "raw": {
            "Version": "https://www.python.org/ftp/python/3.4.1/python-3.4.1rc1-macosx10.5.dmg",
            "Operating System": "macOS",
            "Description": "for Mac OS X 10.5 and later",
            "MD5 Sum": "0d2449cdb0e6d29c86c9b31717964fb2",
            "File Size": "21.8\u00a0MB",
            "GPG": "https://www.python.org/ftp/python/3.4.1/python-3.4.1rc1-macosx10.5.dmg.asc"
        }
    },
    {
        "url": "https://www.python.org/ftp/python/3.4.1/python-3.4.1rc1-macosx10.6.dmg",
        "sha256": "e84f4fcfd2d32fbbebbd207587dbc4f45b1f90e50aba21dfe45e53779f0a220e",
        "release_url": "https://www.python.org/downloads/release/python-341rc1/",
        "raw": {
            "Version": "https://www.python.org/ftp/python/3.4.1/python-3.4.1rc1-macosx10.6.dmg",
            "Operating System": "macOS",
            "Description": "for Mac OS X 10.6 and later",
            "MD5 Sum": "297bae844e63c62a8d7926517eb6adf4",
            "File Size": "21.8\u00a0MB",
            "GPG": "https://www.python.org/ftp/python/3.4.1/python-3.4.1rc1-macosx10.6.dmg.asc"
        }
    },
    {
        "url": "https://www.python.org/ftp/python/3.4.1/python341rc1.chm",
        "sha256": "9497a8fd616a13fa39c03f2b078f0d2528034653cb101be412e8bc37b5a83d8a",
        "release_url": "https://www.python.org/downloads/release/python-341rc1/",
        "raw": {
            "Version": "https://www.python.org/ftp/python/3.4.1/python341rc1.chm",
            "Operating System": "Windows",
            "Description": null,
            "MD5 Sum": "aa70bee4837e4f9d583b8abb85a7b784",
            "File Size": "7.0\u00a0MB",
            "GPG": "https://www.python.org/ftp/python/3.4.1/python341rc1.chm.asc"
        }
    },
    {
        "url": "https://www.python.org/ftp/python/3.4.1/python-3.4.1rc1-pdb.zip",
        "sha256": "a2e8b6fa4ca173359dbdc26de21aed4f4fa9b9676c8d0ba68f0a8a38a8bcf602",
        "release_url": "https://www.python.org/downloads/release/python-341rc1/",
        "raw": {
            "Version": "https://www.python.org/ftp/python/3.4.1/python-3.4.1rc1-pdb.zip",
            "Operating System": "Windows",
            "Description": null,
            "MD5 Sum": "0f87f551df1653afe4119ba75e30fbb0",
            "File Size": "35.0\u00a0MB",
            "GPG": "https://www.python.org/ftp/python/3.4.1/python-3.4.1rc1-pdb.zip.asc"
        }
    },
    {
        "url": "https://www.python.org/ftp/python/3.4.1/python-3.4.1rc1.amd64-pdb.zip",
        "sha256": "e6cad7f3cc196d4aae32aa6d94f5e1ab92cfa7ddb898af873daf96c7c0c49853",
        "release_url": "https://www.python.org/downloads/release/python-341rc1/",
        "raw": {
            "Version": "https://www.python.org/ftp/python/3.4.1/python-3.4.1rc1.amd64-pdb.zip",
            "Operating System": "Windows",
            "Description": null,
            "MD5 Sum": "525f88136ad791f665ef64298b9c8ed0",
            "File Size": "23.0\u00a0MB",
            "GPG": "https://www.python.org/ftp/python/3.4.1/python-3.4.1rc1.amd64-pdb.zip.asc"
        }
    },
    {
        "url": "https://www.python.org/ftp/python/3.4.1/python-3.4.1rc1.msi",
        "sha256": "456faf0654aebf45e98b814b5ea3bc6994d771c4b1305c750ab5c6fb44438d0a",
        "release_url": "https://www.python.org/downloads/release/python-341rc1/",
        "raw": {
            "Version": "https://www.python.org/ftp/python/3.4.1/python-3.4.1rc1.msi",
            "Operating System": "Windows",
            "Description": null,
            "MD5 Sum": "fff0fe9cf48cbd6ef439665991650ed0",
            "File Size": "23.4\u00a0MB",
            "GPG": "https://www.python.org/ftp/python/3.4.1/python-3.4.1rc1.msi.asc"
        }
    },
    {
        "url": "https://www.python.org/ftp/python/3.4.1/python-3.4.1rc1.amd64.msi",
        "sha256": "2ddfe254aaf7dd47ae1ff4affa28df1dfa6c77940043decbd6b69d9cb5846f56",
        "release_url": "https://www.python.org/downloads/release/python-341rc1/",
        "raw": {
            "Version": "https://www.python.org/ftp/python/3.4.1/python-3.4.1rc1.amd64.msi",
            "Operating System": "Windows",
            "Description": "for AMD64/EM64T/x64",
            "MD5 Sum": "d4d7f15976992cc69fcfb4c7d2cf6560",
            "File Size": "24.1\u00a0MB",
            "GPG": "https://www.python.org/ftp/python/3.4.1/python-3.4.1rc1.amd64.msi.asc"
        }
    }
]