[
    {
        "raw": {
            "Description": null,
            "File Size": "21.9\u00a0MB",
            "GPG": "https://www.python.org/ftp/python/3.6.8/Python-3.6.8rc1.tgz.asc",
            "MD5 Sum": "34cd018f6d4ee3e51071bd32e9a17146",
            "Operating System": "Source release",
            "Version": "https://www.python.org/ftp/python/3.6.8/Python-3.6.8rc1.tgz"
        },
        "release_url": "https://www.python.org/downloads/release/python-368rc1/",
        "sha256": "06cbfd4195f9c9a48a9206023161d3ecc32097b2e819bcff605a67977c525c50",
        "url": "https://www.python.org/ftp/python/3.6.8/Python-3.6.8rc1.tgz"
    },
    {
        "raw": {
            "Description": null,
            "File Size": "16.4\u00a0MB",
            "GPG": "https://www.python.org/ftp/python/3.6.8/Python-3.6.8rc1.tar.xz.asc",
            "MD5 Sum": "ba218ed84fa590434a8d8565f32f2c29",
            "Operating System": "Source release",
            "Version": "https://www.python.org/ftp/python/3.6.8/Python-3.6.8rc1.tar.xz"
        },
        "release_url": "https://www.python.org/downloads/release/python-368rc1/",
        "sha256": "11e6a8c9ad26f78b2a6d699eed459db22a944ba8d59a74838a676bac01feea37",
        "url": "https://www.python.org/ftp/python/3.6.8/Python-3.6.8rc1.tar.xz"
    },
    {
        "raw": {
            "Description": "for OS X 10.9 and later",
            "File Size": "25.9\u00a0MB",
            "GPG": "https://www.python.org/ftp/python/3.6.8/python-3.6.8rc1-macosx10.9.pkg.asc",
            "MD5 Sum": "36cbff8077ff886619f7a17099c71dd5",
            "Operating System": "macOS",
            "Version": "https://www.python.org/ftp/python/3.6.8/python-3.6.8rc1-macosx10.9.pkg"
        },
        "release_url": "https://www.python.org/downloads/release/python-368rc1/",
        "sha256": "30f32668eca2c7bfc9281d829c27998d87c448e08d655082dae06d04e5ec380c",
        "url": "https://www.python.org/ftp/python/3.6.8/python-3.6.8rc1-macosx10.9.pkg"
    },
    {
        "raw": {
            "Description": "for Mac OS X 10.6 and later",
            "File Size": "31.8\u00a0MB",
            "GPG": "https://www.python.org/ftp/python/3.6.8/python-3.6.8rc1-macosx10.6.pkg.asc",
            "MD5 Sum": "1d56a1caa1afd6e6ab525b2faecb5740",
            "Operating System": "macOS",
            "Version": "https://www.python.org/ftp/python/3.6.8/python-3.6.8rc1-macosx10.6.pkg"
        },
        "release_url": "https://www.python.org/downloads/release/python-368rc1/",
        "sha256": "0013f4a3ec4eef5d464e12f821be061a0f5c4839c48914899c6bbf57ca8720a7",
        "url": "https://www.python.org/ftp/python/3.6.8/python-3.6.8rc1-macosx10.6.pkg"
    },
    {
        "raw": {
            "Description": null,
            "File Size": "5.3\u00a0MB",
            "GPG": "https://www.python.org/ftp/python/3.6.8/python368rc1.chm.asc",
            "MD5 Sum": "50efdbca7d8c868e922864103f0ef5a3",
            "Operating System": "Windows",
            "Version": "https://www.python.org/ftp/python/3.6.8/python368rc1.chm"
        },
        "release_url": "https://www.python.org/downloads/release/python-368rc1/",
        "sha256": "06dfd71f192f8eafa35556fdd3d5e07deb7762d06ef9aaa340dbf1188af50d3b",
        "url": "https://www.python.org/ftp/python/3.6.8/python368rc1.chm"
    },
    {
        "raw": {
            "Description": null,
            "File Size": "6.1\u00a0MB",
            "GPG": "https://www.python.org/ftp/python/3.6.8/python-3.6.8rc1-embed-win32.zip.asc",
            "MD5 Sum": "1be51e4730d1d44488ed9442fcc5603c",
            "Operating System": "Windows",
            "Version": "https://www.python.org/ftp/python/3.6.8/python-3.6.8rc1-embed-win32.zip"
        },
        "release_url": "https://www.python.org/downloads/release/python-368rc1/",
        "sha256": "622e1b308c6cbc6cc2e7f863ebdc6eaeeed3c7107b9ac723f435b96e4846c166",
        "url": "https://www.python.org/ftp/python/3.6.8/python-3.6.8rc1-embed-win32.zip"
    },
    {
        "raw": {
            "Description": null,
            "File Size": "27.0\u00a0MB",
            "GPG": "https://www.python.org/ftp/python/3.6.8/python-3.6.8rc1.exe.asc",
            "MD5 Sum": "ed21608ff5a5b60eb933bd6b24d59279",
            "Operating System": "Windows",
            "Version": "https://www.python.org/ftp/python/3.6.8/python-3.6.8rc1.exe"
        },
        "release_url": "https://www.python.org/downloads/release/python-368rc1/",
        "sha256": "0e93446436562f683cfb43ffa43ecddddd3694b2c8c4b840ef3bd399ebcafb3c",
        "url": "https://www.python.org/ftp/python/3.6.8/python-3.6.8rc1.exe"
    },
    {
        "raw": {
            "Description": null,
            "File Size": "1.2\u00a0MB",
            "GPG": "https://www.python.org/ftp/python/3.6.8/python-3.6.8rc1-webinstall.exe.asc",
            "MD5 Sum": "782b3df069a6ec6f92d09938c5d2a379",
            "Operating System": "Windows",
            "Version": "https://www.python.org/ftp/python/3.6.8/python-3.6.8rc1-webinstall.exe"
        },
        "release_url": "https://www.python.org/downloads/release/python-368rc1/",
        "sha256": "f64bf1cf15632011fc377849437b3d1d4671f3b62e3e8673e6a87c0d2626632d",
        "url": "https://www.python.org/ftp/python/3.6.8/python-3.6.8rc1-webinstall.exe"
    },
    {
        "raw": {
            "Description": "for AMD64/EM64T/x64",
            "File Size": "6.9\u00a0MB",
            "GPG": "https://www.python.org/ftp/python/3.6.8/python-3.6.8rc1-embed-amd64.zip.asc",
            "MD5 Sum": "2b669a13361d04f4acf1113bf25d3f98",
            "Operating System": "Windows",
            "Version": "https://www.python.org/ftp/python/3.6.8/python-3.6.8rc1-embed-amd64.zip"
        },
        "release_url": "https://www.python.org/downloads/release/python-368rc1/",
        "sha256": "10b953e8d9101c7941e35ca235ef1ee23fc1eb288d14703f5dd3b55e882807b8",
        "url": "https://www.python.org/ftp/python/3.6.8/python-3.6.8rc1-embed-amd64.zip"
    },
    {
        "raw": {
            "Description": "for AMD64/EM64T/x64",
            "File Size": "28.0\u00a0MB",
            "GPG": "https://www.python.org/ftp/python/3.6.8/python-3.6.8rc1-amd64.exe.asc",
            "MD5 Sum": "811d870f227142a19e347cdd37fc6a0b",
            "Operating System": "Windows",
            "Version": "https://www.python.org/ftp/python/3.6.8/python-3.6.8rc1-amd64.exe"
        },
        "release_url": "https://www.python.org/downloads/release/python-368rc1/",
        "sha256": "f50c9dd1b5f2ac2f2663accf57d9463aa06a227b41bc1e1b41ba0a08c00cf64d",
        "url": "https://www.python.org/ftp/python/3.6.8/python-3.6.8rc1-amd64.exe"
    },
    {
        "raw": {
            "Description": "for AMD64/EM64T/x64",
            "File Size": "1.3\u00a0MB",
            "GPG": "https://www.python.org/ftp/python/3.6.8/python-3.6.8rc1-amd64-webinstall.exe.asc",
            "MD5 Sum": "00352454af164d53db8a066764252bc1",
            "Operating System": "Windows",
            "Version": "https://www.python.org/ftp/python/3.6.8/python-3.6.8rc1-amd64-webinstall.exe"
        },
        "release_url": "https://www.python.org/downloads/release/python-368rc1/",
        "sha256": "91299fade023f0059a2a158f6768c243cd40cb5b6e14242827eea6d0bf8d97d1",
        "url": "https://www.python.org/ftp/python/3.6.8/python-3.6.8rc1-amd64-webinstall.exe"
    }
]