[
    {
        "raw": {
            "Description": null,
            "File Size": "23.0\u00a0MB",
            "GPG": "https://www.python.org/ftp/python/3.8.4/Python-3.8.4.tgz.asc",
            "MD5 Sum": "387e63fe42c40a29e3408ce231315516",
            "Operating System": "Source release",
            "Version": "https://www.python.org/ftp/python/3.8.4/Python-3.8.4.tgz"
        },
        "release_url": "https://www.python.org/downloads/release/python-384/",
        "sha256": "32c4d9817ef11793da4d0d95b3191c4db81d2e45544614e8449255ca9ae3cc18",
        "url": "https://www.python.org/ftp/python/3.8.4/Python-3.8.4.tgz"
    },
    {
        "raw": {
            "Description": null,
            "File Size": "17.2\u00a0MB",
            "GPG": "https://www.python.org/ftp/python/3.8.4/Python-3.8.4.tar.xz.asc",
            "MD5 Sum": "e16df33cd7b58702e57e137f8f5d13e7",
            "Operating System": "Source release",
            "Version": "https://www.python.org/ftp/python/3.8.4/Python-3.8.4.tar.xz"
        },
        "release_url": "https://www.python.org/downloads/release/python-384/",
        "sha256": "5f41968a95afe9bc12192d7e6861aab31e80a46c46fa59d3d837def6a4cd4d37",
        "url": "https://www.python.org/ftp/python/3.8.4/Python-3.8.4.tar.xz"
    },
    {
        "raw": {
            "Description": "for OS X 10.9 and later",
            "File Size": "28.8\u00a0MB",
            "GPG": "https://www.python.org/ftp/python/3.8.4/python-3.8.4-macosx10.9.pkg.asc",
            "MD5 Sum": "8464bc5341d3444b2ccad001d88b752b",
            "Operating System": "macOS",
            "Version": "https://www.python.org/ftp/python/3.8.4/python-3.8.4-macosx10.9.pkg"
        },
        "release_url": "https://www.python.org/downloads/release/python-384/",
        "sha256": "ef5fccda6e955e60506c8460b85a80dd602789be79531e5c1ba5ba8e81e1e3bd",
        "url": "https://www.python.org/ftp/python/3.8.4/python-3.8.4-macosx10.9.pkg"
    },
    {
        "raw": {
            "Description": null,
            "File Size": "8.1\u00a0MB",
            "GPG": "https://www.python.org/ftp/python/3.8.4/python384.chm.asc",
            "MD5 Sum": "bf7942cdd74f34aa4f485730a714cc47",
            "Operating System": "Windows",
            "Version": "https://www.python.org/ftp/python/3.8.4/python384.chm"
        },
        "release_url": "https://www.python.org/downloads/release/python-384/",
        "sha256": "2f266ef57307ed3580562cd2e881f6e11d460dfd680d49a636ecd0e752030005",
        "url": "https://www.python.org/ftp/python/3.8.4/python384.chm"
    },
    {
        "raw": {
            "Description": null,
            "File Size": "7.0\u00a0MB",
            "GPG": "https://www.python.org/ftp/python/3.8.4/python-3.8.4-embed-win32.zip.asc",
            "MD5 Sum": "910c307f58282aaa88a2e9df38083ed2",
            "Operating System": "Windows",
            "Version": "https://www.python.org/ftp/python/3.8.4/python-3.8.4-embed-win32.zip"
        },
        "release_url": "https://www.python.org/downloads/release/python-384/",
        "sha256": "ad874d80e2ded1dc1be35a0e233a065825684a0bba71e9e583fb64cfc161c0e0",
        "url": "https://www.python.org/ftp/python/3.8.4/python-3.8.4-embed-win32.zip"
    },
    {
        "raw": {
            "Description": null,
            "File Size": "25.5\u00a0MB",
            "GPG": "https://www.python.org/ftp/python/3.8.4/python-3.8.4.exe.asc",
            "MD5 Sum": "c3d71a80f518cfba4d038de53bca2734",
            "Operating System": "Windows",
            "Version": "https://www.python.org/ftp/python/3.8.4/python-3.8.4.exe"
        },
        "release_url": "https://www.python.org/downloads/release/python-384/",
        "sha256": "cd0664574efd4a1ed29d10ee10e1dc7a45b8922e03191344cf9fbe179fceada3",
        "url": "https://www.python.org/ftp/python/3.8.4/python-3.8.4.exe"
    },
    {
        "raw": {
            "Description": null,
            "File Size": "1.3\u00a0MB",
            "GPG": "https://www.python.org/ftp/python/3.8.4/python-3.8.4-webinstall.exe.asc",
            "MD5 Sum": "075a93add0ac3d070b113f71442ace37",
            "Operating System": "Windows",
            "Version": "https://www.python.org/ftp/python/3.8.4/python-3.8.4-webinstall.exe"
        },
        "release_url": "https://www.python.org/downloads/release/python-384/",
        "sha256": "fd3aca7fa17e752e5c100e334cc5c0a409c03a7ff1f36233ab0c161ed036bbf8",
        "url": "https://www.python.org/ftp/python/3.8.4/python-3.8.4-webinstall.exe"
    },
    {
        "raw": {
            "Description": "for AMD64/EM64T/x64",
            "File Size": "7.8\u00a0MB",
            "GPG": "https://www.python.org/ftp/python/3.8.4/python-3.8.4-embed-amd64.zip.asc",
            "MD5 Sum": "c68f60422a0e43dabf54b84a0e92ed6a",
            "Operating System": "Windows",
            "Version": "https://www.python.org/ftp/python/3.8.4/python-3.8.4-embed-amd64.zip"
        },
        "release_url": "https://www.python.org/downloads/release/python-384/",
        "sha256": "18acd42077facdb5ccbada9581828e0b42f742c70a62f61522cd19c49912c7bf",
        "url": "https://www.python.org/ftp/python/3.8.4/python-3.8.4-embed-amd64.zip"
    },
    {
        "raw": {
            "Description": "for AMD64/EM64T/x64",
            "File Size": "26.6\u00a0MB",
            "GPG": "https://www.python.org/ftp/python/3.8.4/python-3.8.4-amd64.exe.asc",
            "MD5 Sum": "12297fb08088d1002f7e93a93fd779c6",
            "Operating System": "Windows",
            "Version": "https://www.python.org/ftp/python/3.8.4/python-3.8.4-amd64.exe"
        },
        "release_url": "https://www.python.org/downloads/release/python-384/",
        "sha256": "24cead226c8b3de579e246aa4152bd6c2ff8a613a65998eac8b66920d9821919",
        "url": "https://www.python.org/ftp/python/3.8.4/python-3.8.4-amd64.exe"
    },
    {
        "raw": {
            "Description": "for AMD64/EM64T/x64",
            "File Size": "1.3\u00a0MB",
            "GPG": "https://www.python.org/ftp/python/3.8.4/python-3.8.4-amd64-webinstall.exe.asc",
            "MD5 Sum": "7c382afb4d8faa0a82973e44caf02949",
            "Operating System": "Windows",
            "Version": "https://www.python.org/ftp/python/3.8.4/python-3.8.4-amd64-webinstall.exe"
        },
        "release_url": "https://www.python.org/downloads/release/python-384/",
        "sha256": "239d7b7878f9fab9b3ac6e4e91ef06f2315a43b59d120c47b1a53f591820dcbd",
        "url": "https://www.python.org/ftp/python/3.8.4/python-3.8.4-amd64-webinstall.exe"
    }
]