[
    {
        "raw": {
            "description": null,
            "filesize": 8568303,
            "md5": "4aeeebd7cc8dd90d61e7cfdda9cb9422",
            "sha256": null,
            "sigstore": null,
            "slug": "python-383",
            "url": "https://www.python.org/ftp/python/3.8.3/python383.chm"
        },
        "sha256": "8dcc9fb50783a914c6eaba98faf15e41efc12fafcb3a6587333db860451c2ff3"
    },
    {
        "raw": {
            "description": null,
            "filesize": 7330315,
            "md5": "8ee09403ec0cc2e89d43b4a4f6d1521e",
            "sha256": null,
            "sigstore": null,
            "slug": "python-383",
            "url": "https://www.python.org/ftp/python/3.8.3/python-3.8.3-embed-win32.zip"
        },
        "sha256": "3354e89fc64f3248a3187ab2e75b03ea6b67d89af104c5dff007fe8df909de2b"
    },
    {
        "raw": {
            "description": null,
            "filesize": 26744744,
            "md5": "452373e2c467c14220efeb10f40c231f",
            "sha256": null,
            "sigstore": null,
            "slug": "python-383",
            "url": "https://www.python.org/ftp/python/3.8.3/python-3.8.3.exe"
        },
        "sha256": "e5ea9f5646fe3cff2621b61a55a98ea5b3e9ca7dd7cc14c13535e55c88686872"
    },
    {
        "raw": {
            "description": null,
            "filesize": 1325800,
            "md5": "fe72582bbca3dbe07451fd05ece1d752",
            "sha256": null,
            "sigstore": null,
            "slug": "python-383",
            "url": "https://www.python.org/ftp/python/3.8.3/python-3.8.3-webinstall.exe"
        },
        "sha256": "0eafeff1c8f685edcfd9bc9e935b36c2fade56c397bfa9a86277b3fc386d709c"
    },
    {
        "raw": {
            "description": "for AMD64/EM64T/x64",
            "filesize": 8175801,
            "md5": "c12ffe7f4c1b447241d5d2aedc9b5d01",
            "sha256": null,
            "sigstore": null,
            "slug": "python-383",
            "url": "https://www.python.org/ftp/python/3.8.3/python-3.8.3-embed-amd64.zip"
        },
        "sha256": "7f8c29563dae48a07ea3242a6a19b7b5b8519a16fd711e719a8f9680f342279a"
    },
    {
        "raw": {
            "description": "for AMD64/EM64T/x64",
            "filesize": 27805800,
            "md5": "fd2458fa0e9ead1dd9fbc2370a42853b",
            "sha256": null,
            "sigstore": null,
            "slug": "python-383",
            "url": "https://www.python.org/ftp/python/3.8.3/python-3.8.3-amd64.exe"
        },
        "sha256": "c74898382a5192d4b506767cbb4b41b8e80b734b8a7ce1fbb13e4aba8ffe5bf6"
    },
    {
        "raw": {
            "description": "for AMD64/EM64T/x64",
            "filesize": 1364136,
            "md5": "17e989d2fecf7f9f13cf987825b695c4",
            "sha256": null,
            "sigstore": null,
            "slug": "python-383",
            "url": "https://www.python.org/ftp/python/3.8.3/python-3.8.3-amd64-webinstall.exe"
        },
        "sha256": "73bd7cfe395adcba5a8ffe2bdf88a2fb60f03a447b887dd197e704b291da16bd"
    },
    {
        "raw": {
            "description": "for OS X 10.9 and later",
            "filesize": 30119781,
            "md5": "dd5e7f64e255d21f8d407f39a7a41ba9",
            "sha256": null,
            "sigstore": null,
            "slug": "python-383",
            "url": "https://www.python.org/ftp/python/3.8.3/python-3.8.3-macosx10.9.pkg"
        },
        "sha256": "a563cdb78a7ac5e7879f5a6a8acb363583077bfb1d9fa1e2981b159adfba3cb5"
    },
    {
        "raw": {
            "description": null,
            "filesize": 24067487,
            "md5": "a7c10a2ac9d62de75a0ca5204e2e7d07",
            "sha256": null,
            "sigstore": null,
            "slug": "python-383",
            "url": "https://www.python.org/ftp/python/3.8.3/Python-3.8.3.tgz"
        },
        "sha256": "6af6d4d2e010f9655518d0fc6738c7ff7069f10a4d2fbd55509e467f092a8b90"
    },
    {
        "raw": {
            "description": null,
            "filesize": 17912964,
            "md5": "3000cf50aaa413052aef82fd2122ca78",
            "sha256": null,
            "sigstore": null,
            "slug": "python-383",
            "url": "https://www.python.org/ftp/python/3.8.3/Python-3.8.3.tar.xz"
        },
        "sha256": "dfab5ec723c218082fe3d5d7ae17ecbdebffa9a1aea4d64aa3a2ecdd2e795864"
    }
]